pictoken/__init__.py
pictoken/const.py
pictoken/enums.py
pictoken/models.py
pictoken/py.typed
pictoken/utils.py
pictoken-0.1.0.dist-info/METADATA
pictoken-0.1.0.dist-info/WHEEL
pictoken-0.1.0.dist-info/licenses/LICENSE
pictoken-0.1.0.dist-info/RECORD
