Metadata-Version: 2.3
Name: pictoken
Version: 0.1.0
Summary: Calculate image tokens for (Azure) OpenAI models. Offers multiple utilities to resize images to reduce token usage.
Project-URL: Homepage, https://github.com/iMicknl/pictoken
Project-URL: Repository, https://github.com/iMicknl/pictoken
Author-email: Mick Vleeshouwer <mick@imick.nl>
License: MIT License
License-File: LICENSE
Keywords: Azure,GPT4o,Image,LLM,OpenAI,VLLM
Classifier: Development Status :: 4 - Beta
Classifier: Programming Language :: Python
Requires-Python: >=3.9
Requires-Dist: backports-strenum>=1.3.1; python_version < '3.11'
Requires-Dist: pillow>=10.4.0
